arpes/__init__.py
arpes/all.py
arpes/bootstrap.py
arpes/config.py
arpes/constants.py
arpes/exceptions.py
arpes/io.py
arpes/laser.py
arpes/load_pxt.py
arpes/optics.py
arpes/provenance.py
arpes/repair.py
arpes/simulation.py
arpes/trace.py
arpes/typing.py
arpes/widgets.py
arpes/workflow.py
arpes/xarray_extensions.py
arpes/analysis/__init__.py
arpes/analysis/align.py
arpes/analysis/all.py
arpes/analysis/background.py
arpes/analysis/band_analysis.py
arpes/analysis/band_analysis_utils.py
arpes/analysis/decomposition.py
arpes/analysis/deconvolution.py
arpes/analysis/derivative.py
arpes/analysis/filters.py
arpes/analysis/gap.py
arpes/analysis/general.py
arpes/analysis/kfermi.py
arpes/analysis/mask.py
arpes/analysis/moire.py
arpes/analysis/path.py
arpes/analysis/pocket.py
arpes/analysis/resolution.py
arpes/analysis/sarpes.py
arpes/analysis/savitzky_golay.py
arpes/analysis/self_energy.py
arpes/analysis/shirley.py
arpes/analysis/statistics.py
arpes/analysis/tarpes.py
arpes/analysis/xps.py
arpes/corrections/__init__.py
arpes/corrections/background.py
arpes/corrections/fermi_edge_corrections.py
arpes/deep_learning/__init__.py
arpes/deep_learning/formatters.py
arpes/deep_learning/interpret.py
arpes/deep_learning/io.py
arpes/deep_learning/transforms.py
arpes/deep_learning/models/__init__.py
arpes/deep_learning/models/regression.py
arpes/endstations/__init__.py
arpes/endstations/fits_utils.py
arpes/endstations/igor_utils.py
arpes/endstations/nexus_utils.py
arpes/endstations/plugin/ALG_main.py
arpes/endstations/plugin/ALG_spin_ToF.py
arpes/endstations/plugin/ANTARES.py
arpes/endstations/plugin/Elettra_spectromicroscopy.py
arpes/endstations/plugin/HERS.py
arpes/endstations/plugin/MAESTRO.py
arpes/endstations/plugin/MBS.py
arpes/endstations/plugin/SToF_DLD.py
arpes/endstations/plugin/__init__.py
arpes/endstations/plugin/example_data.py
arpes/endstations/plugin/fallback.py
arpes/endstations/plugin/igor_export.py
arpes/endstations/plugin/igor_plugin.py
arpes-3.0.1.dist-info/LICENSE
arpes-3.0.1.dist-info/METADATA
arpes-3.0.1.dist-info/WHEEL
arpes-3.0.1.dist-info/dependency_links.txt
arpes-3.0.1.dist-info/top_level.txt
arpes-3.0.1.dist-info/RECORD
