Metadata-Version: 2.1
Name: arpes
Version: 3.0.1
Summary: Modular data analysis code for angle resolved photoemission spectroscopy (ARPES)
Home-page: https://gitlab.com/lanzara-group/python-arpes
Author: Conrad Stansbury
Author-email: chstan@berkeley.edu
License: GPLv3
Platform: UNKNOWN
Classifier: License :: OSI Approved :: GNU General Public License v3 (GPLv3)
Classifier: Programming Language :: Python
Classifier: Programming Language :: Python :: 3
Classifier: Programming Language :: Python :: 3.8
Classifier: Programming Language :: Python :: Implementation :: CPython
Classifier: Natural Language :: English
Classifier: Intended Audience :: Science/Research
Classifier: Intended Audience :: Developers
Classifier: Operating System :: MacOS :: MacOS X
Classifier: Operating System :: Microsoft :: Windows :: Windows 7
Classifier: Operating System :: Microsoft :: Windows :: Windows 8
Classifier: Operating System :: Microsoft :: Windows :: Windows 10
Classifier: Operating System :: Unix
Classifier: Operating System :: POSIX :: Linux
Classifier: Topic :: Scientific/Engineering :: Physics
Classifier: Topic :: Scientific/Engineering
Classifier: Topic :: Software Development :: Libraries :: Python Modules
Requires-Python: >=3.8.0,<3.9
License-File: LICENSE
Requires-Dist: astropy
Requires-Dist: xarray (>=0.16.1)
Requires-Dist: h5py (>=3.2.1)
Requires-Dist: pyqtgraph (<0.13.0,>=0.12.0)
Requires-Dist: PyQt5 (==5.15)
Requires-Dist: netCDF4 (<2.0.0,>=1.5.0)
Requires-Dist: colorcet
Requires-Dist: pint
Requires-Dist: pandas
Requires-Dist: numpy (<2.0.0,>=1.20.0)
Requires-Dist: scipy (<2.0.0,>=1.6.0)
Requires-Dist: lmfit (<2.0.0,>=1.0.0)
Requires-Dist: scikit-learn
Requires-Dist: matplotlib (>=3.0.3)
Requires-Dist: bokeh (<3.0.0,>=2.0.0)
Requires-Dist: ipywidgets (<8.0.0,>=7.0.1)
Requires-Dist: packaging
Requires-Dist: colorama
Requires-Dist: imageio
Requires-Dist: titlecase
Requires-Dist: tqdm
Requires-Dist: rx
Requires-Dist: dill
Requires-Dist: ase (<4.0.0,>=3.20.0)
Requires-Dist: numba (<1.0.0,>=0.53.0)
